README.rst
setup.py
locker/__init__.py
locker/locker.py
python_locker.egg-info/PKG-INFO
python_locker.egg-info/SOURCES.txt
python_locker.egg-info/dependency_links.txt
python_locker.egg-info/requires.txt
python_locker.egg-info/top_level.txt