Metadata-Version: 1.1
Name: python-locker
Version: 1.0.1
Summary: A place to keep your valuables.
Home-page: https://github.com/Coal0/Locker
Author: coal0
Author-email: githubcoal@protonmail.com
License: MIT
Download-URL: https://github.com/Coal0/Locker/releases/tag/v1.0.0
Keywords: locker,secure,encrypt,storage
Platform: UNKNOWN
Classifier: Development Status :: 5 - Production/Stable
Classifier: Intended Audience :: Developers
Classifier: Topic :: Security
Classifier: License :: OSI Approved :: MIT License
Classifier: Programming Language :: Python :: 3
